discogrify/__init__.py
discogrify/auth_config
discogrify/cli.py
discogrify/config.py
discogrify/spotify_client.py
discogrify/utils.py
tests/__init__.py
tests/conftest.py
tests/test_cli.py
tests/test_utils.py
tests/tools/__init__.py
tests/tools/authenticate.py
discogrify-0.0.11.dist-info/METADATA
discogrify-0.0.11.dist-info/WHEEL
discogrify-0.0.11.dist-info/entry_points.txt
discogrify-0.0.11.dist-info/top_level.txt
discogrify-0.0.11.dist-info/RECORD
