Metadata-Version: 2.1
Name: discogrify
Version: 0.0.11
Summary: Create discographies on Spotify
Home-page: https://github.com/Ch00k/discogrify
Author: Andrii Yurchuk
Author-email: ay@mntw.re
License: Unlicense
Keywords: spotify discography playlist
Classifier: Topic :: Multimedia :: Sound/Audio
Classifier: Development Status :: 4 - Beta
Classifier: Intended Audience :: End Users/Desktop
Classifier: License :: OSI Approved :: The Unlicense (Unlicense)
Classifier: Natural Language :: English
Classifier: Programming Language :: Python :: 3
Classifier: Programming Language :: Python :: 3.8
Classifier: Programming Language :: Python :: 3.9
Classifier: Programming Language :: Python :: 3.10
Classifier: Programming Language :: Python :: 3.11
Classifier: Programming Language :: Python :: Implementation :: CPython
Classifier: Programming Language :: Python :: Implementation :: PyPy
Classifier: Operating System :: Microsoft :: Windows
Classifier: Operating System :: POSIX
Classifier: Operating System :: POSIX :: BSD
Classifier: Operating System :: POSIX :: Linux
Classifier: Operating System :: MacOS :: MacOS X
Requires-Dist: async-timeout (==4.0.2)
Requires-Dist: certifi (==2022.12.7)
Requires-Dist: charset-normalizer (==2.1.1)
Requires-Dist: click (==8.1.3)
Requires-Dist: environs (==9.5.0)
Requires-Dist: idna (==3.4)
Requires-Dist: marshmallow (==3.19.0)
Requires-Dist: packaging (==23.0)
Requires-Dist: python-dotenv (==0.21.1)
Requires-Dist: redis (==4.4.0)
Requires-Dist: requests (==2.28.1)
Requires-Dist: six (==1.16.0)
Requires-Dist: spotipy (==2.22.0)
Requires-Dist: tabulate (==0.9.0)
Requires-Dist: urllib3 (==1.26.13)
